[
    {
        "5_fc": 0.11982761323451996,
        "4_Layer3": 0.008723517879843712,
        "3_Layer2": 0.011826198548078537,
        "2_Layer1": 0.0174794252961874,
        "1_conv1": 0.20903989672660828
    },
    {
        "5_fc": 0.11446864157915115,
        "4_Layer3": 0.01191402692347765,
        "3_Layer2": 0.023871805518865585,
        "2_Layer1": 0.034252412617206573,
        "1_conv1": 0.314311146736145
    },
    {
        "5_fc": NaN,
        "4_Layer3": NaN,
        "3_Layer2": NaN,
        "2_Layer1": NaN,
        "1_conv1": NaN
    },
    {
        "5_fc": NaN,
        "4_Layer3": NaN,
        "3_Layer2": NaN,
        "2_Layer1": NaN,
        "1_conv1": NaN
    },
    {
        "5_fc": NaN,
        "4_Layer3": NaN,
        "3_Layer2": NaN,
        "2_Layer1": NaN,
        "1_conv1": NaN
    }
]